cuckooutils.py
cuckoomodifiedutils-1.0.3.dist-info/DESCRIPTION.rst
cuckoomodifiedutils-1.0.3.dist-info/METADATA
cuckoomodifiedutils-1.0.3.dist-info/RECORD
cuckoomodifiedutils-1.0.3.dist-info/WHEEL
cuckoomodifiedutils-1.0.3.dist-info/metadata.json
cuckoomodifiedutils-1.0.3.dist-info/top_level.txt
