Metadata-Version: 2.0
Name: cuckoomodifiedutils
Version: 1.0.3
Summary: A simple module for the API of the Brad Spengler fork of Cuckoo.
Home-page: https://github.com/seanthegeek/cuckoo-modified-utils
Author: Sean Whalen
Author-email: whalenster@gmail.com
License: Apache 2.0
Keywords: ActiveDirectory,WindowsServer,authentication,LDAP
Platform: UNKNOWN
Classifier: Development Status :: 5 - Production/Stable
Classifier: Topic :: Security
Classifier: Intended Audience :: Developers
Classifier: Intended Audience :: System Administrators
Classifier: Operating System :: OS Independent
Classifier: License :: OSI Approved :: Apache Software License
Classifier: Programming Language :: Python :: 2
Classifier: Programming Language :: Python :: 2.6
Classifier: Programming Language :: Python :: 2.7
Classifier: Programming Language :: Python :: 3
Classifier: Programming Language :: Python :: 3.3
Classifier: Programming Language :: Python :: 3.4
Classifier: Programming Language :: Python :: 3.5
Requires-Dist: requests
